data_generator/__init__.py
data_generator/apps.py
data_generator/constants/__init__.py
data_generator/constants/ansi_colors.py
data_generator/constants/default_settings.py
data_generator/constants/types.py
data_generator/generators/__init__.py
data_generator/generators/data_generator.py
data_generator/management/__init__.py
data_generator/management/commands/__init__.py
data_generator/management/commands/generate_data.py
data_generator/settings/__init__.py
data_generator/settings/check.py
data_generator/settings/conf.py
data_generator/tests/__init__.py
data_generator/tests/commands/__init__.py
data_generator/tests/commands/test_generate_data.py
data_generator/tests/conftest.py
data_generator/tests/constants.py
data_generator/tests/generators/__init__.py
data_generator/tests/generators/test_model_data_generator.py
data_generator/tests/settings/__init__.py
data_generator/tests/settings/test_check.py
data_generator/tests/setup.py
data_generator/tests/validators/__init__.py
data_generator/tests/validators/test_config_validators.py
data_generator/validators/__init__.py
data_generator/validators/config_validators.py
dj_data_generator-1.0.2.dist-info/AUTHORS.md
dj_data_generator-1.0.2.dist-info/LICENSE
dj_data_generator-1.0.2.dist-info/METADATA
dj_data_generator-1.0.2.dist-info/WHEEL
dj_data_generator-1.0.2.dist-info/RECORD
