Metadata-Version: 2.3
Name: dj-data-generator
Version: 1.0.2
Summary: A package for generating fake data
License: MIT
Keywords: data,data generator,django data generator,fake data,generator
Author: ARYAN-NIKNEZHAD
Author-email: aryan513966@gmail.com
Requires-Python: >=3.9
Classifier: Development Status :: 3 - Alpha
Classifier: Environment :: Web Environment
Classifier: Framework :: Django
Classifier: Framework :: Django :: 4.2
Classifier: Framework :: Django :: 5.0
Classifier: Framework :: Django :: 5.1
Classifier: Intended Audience :: Developers
Classifier: License :: OSI Approved :: MIT License
Classifier: Operating System :: OS Independent
Classifier: Programming Language :: Python
Classifier: Programming Language :: Python :: 3 :: Only
Classifier: Programming Language :: Python :: 3.9
Classifier: Programming Language :: Python :: 3.10
Classifier: Programming Language :: Python :: 3.11
Classifier: Programming Language :: Python :: 3.12
Classifier: Programming Language :: Python :: 3.13
Classifier: Topic :: Software Development :: Libraries :: Python Modules
Requires-Dist: django (>=4.2,<5.0) ; python_version == "3.9"
Requires-Dist: django (>=4.2,<5.3) ; python_version >= "3.10"
Project-URL: Changelog, https://github.com/lazarus-org/dj-data-generator/blob/main/CHANGELOG.md
Project-URL: Issues, https://github.com/lazarus-org/dj-data-generator/issues
Project-URL: Source Code, https://github.com/Lazarus-org/dj-data-generator
